README.md
setup.py
calc2/__init__.py
calc2/__main__.py
calc2.egg-info/PKG-INFO
calc2.egg-info/SOURCES.txt
calc2.egg-info/dependency_links.txt
calc2.egg-info/entry_points.txt
calc2.egg-info/requires.txt
calc2.egg-info/top_level.txt
calc2/electricity/ac3.py
calc2/electricity/battery_capacity_ah.py
calc2/electricity/battery_capacity_kwh.py
calc2/electricity/electrical.py
calc2/electricity/hioki.py
calc2/electricity/pulse.py
calc2/electricity/short_test.py