Metadata-Version: 2.1
Name: calc2
Version: 0.3.0.3
Summary: This Python library can perform various calculations for scientific field. 
Home-page: https://tanaka0079.github.io/libs/python/calc2/docs/html/index.html
Author: Nishizumi
Author-email: daiman003@yahoo.co.jp
License: UNKNOWN
Keywords: electricity
Platform: UNKNOWN
Classifier: Development Status :: 2 - Pre-Alpha
Classifier: Natural Language :: English
Classifier: License :: OSI Approved :: MIT License
Classifier: Programming Language :: Python :: 3.8
Classifier: Operating System :: OS Independent
